django_scaffolding_tools/__init__.py
django_scaffolding_tools/_experimental/__init__.py
django_scaffolding_tools/_experimental/backup_envs/__init__.py
django_scaffolding_tools/_experimental/backup_envs/backups.py
django_scaffolding_tools/_experimental/backup_envs/exceptions.py
django_scaffolding_tools/_experimental/backup_envs/gdrive.py
django_scaffolding_tools/_experimental/backup_envs/google_drive.py
django_scaffolding_tools/_experimental/click_demo/__init__.py
django_scaffolding_tools/_experimental/click_demo/print_single_line.py
django_scaffolding_tools/_experimental/docker/__init__.py
django_scaffolding_tools/_experimental/docker/clean_postgres.py
django_scaffolding_tools/_experimental/docker/commnads.py
django_scaffolding_tools/_experimental/docker/containers.py
django_scaffolding_tools/_experimental/docker/enums.py
django_scaffolding_tools/builders.py
django_scaffolding_tools/cli.py
django_scaffolding_tools/django/__init__.py
django_scaffolding_tools/django/builders.py
django_scaffolding_tools/django/cli.py
django_scaffolding_tools/django/handlers.py
django_scaffolding_tools/django/parsers.py
django_scaffolding_tools/django/utils.py
django_scaffolding_tools/django/writers.py
django_scaffolding_tools/django_scaffolding_tools.py
django_scaffolding_tools/enums.py
django_scaffolding_tools/exceptions.py
django_scaffolding_tools/models.py
django_scaffolding_tools/parsers.py
django_scaffolding_tools/patterns.py
django_scaffolding_tools/pydantic/StatusChangeEvent.csv
django_scaffolding_tools/pydantic/__init__.py
django_scaffolding_tools/pydantic/main.py
django_scaffolding_tools/pydantic/schemas.py
django_scaffolding_tools/templates/drf_model_serializers.py.j2
django_scaffolding_tools/templates/drf_serializers.py.j2
django_scaffolding_tools/templates/enums.py.j2
django_scaffolding_tools/templates/serializers.py.j2
django_scaffolding_tools/utils/__init__.py
django_scaffolding_tools/utils/assert_utils.py
django_scaffolding_tools/utils/core.py
django_scaffolding_tools-0.11.1.dist-info/AUTHORS.rst
django_scaffolding_tools-0.11.1.dist-info/LICENSE
django_scaffolding_tools-0.11.1.dist-info/METADATA
django_scaffolding_tools-0.11.1.dist-info/WHEEL
django_scaffolding_tools-0.11.1.dist-info/RECORD
