Metadata-Version: 2.1
Name: django-scaffolding-tools
Version: 0.11.1
Summary: Tools to quickly scaffold django apps and templates.
License: MIT
Author: Luis C. Berrocal
Author-email: luis.berrocal.1942@gmail.com
Requires-Python: >=3.10,<4.0
Classifier: Development Status :: 2 - Pre-Alpha
Classifier: Intended Audience :: Developers
Classifier: License :: OSI Approved :: MIT License
Classifier: Natural Language :: English
Classifier: Programming Language :: Python :: 3
Classifier: Programming Language :: Python :: 3.10
Classifier: Programming Language :: Python :: 3.11
Classifier: Programming Language :: Python :: 3.12
Classifier: Programming Language :: Python :: 3.13
Requires-Dist: click (>=8.1.8,<9.0.0)
Requires-Dist: jinja2 (>=3.1.5,<4.0.0)
Requires-Dist: pydantic (>=2.10.5,<3.0.0)
Requires-Dist: pyhumps (>=3.8.0,<4.0.0)
